Metadata-Version: 2.1
Name: crispector2
Version: 2.1.2
Summary: CRISPECTOR2 - Genome Editing Analysis Tool, with allele extension
Author: Guy Assa
Author-email: guyassa@gmail.com
Project-URL: repository, https://github.com/theAguy/crispector2
Keywords: crispector2
Classifier: Development Status :: 4 - Beta
Classifier: Intended Audience :: Science/Research
Classifier: Topic :: Scientific/Engineering :: Bio-Informatics
Classifier: License :: Other/Proprietary License
Classifier: Natural Language :: English
Classifier: Programming Language :: Python :: 3.8
License-File: LICENSE
Requires-Dist: Click >=7.0
Requires-Dist: matplotlib >=3.1.2
Requires-Dist: seaborn >=0.9.0
Requires-Dist: pyyaml >=5.1.2
Requires-Dist: plotly >=4.3.0
Requires-Dist: numpy >=1.12.1
Requires-Dist: pandas >=0.24.2
Requires-Dist: biopython <=1.79,>=1.74
Requires-Dist: scipy >=1.2.1
Requires-Dist: jinja2 >=3.1.2
Requires-Dist: tqdm >=4.66.0
Requires-Dist: mpmath >=1.3.0
Requires-Dist: statsmodels >=0.13.2
Requires-Dist: edlib >=1.3.9
